dubai_real_estate/__init__.py
dubai_real_estate/_version.py
dubai_real_estate/install.py
dubai_real_estate/connection/__init__.py
dubai_real_estate/connection/clients.py
dubai_real_estate/connection/manager.py
dubai_real_estate/connection/storage.py
dubai_real_estate/connection/types.py
dubai_real_estate/magic/__init__.py
dubai_real_estate/magic/sql_magic.py
dubai_real_estate/sql/__init__.py
dubai_real_estate/sql/parser.py
dubai_real_estate/sql_files/__init__.py
dubai_real_estate/sql_files/functions/__init__.py
dubai_real_estate/sql_files/functions/format/__init__.py
dubai_real_estate/sql_files/functions/format/format_type.sql
dubai_real_estate/sql_files/functions/lang/__init__.py
dubai_real_estate/sql_files/functions/lang/check.sql
dubai_real_estate/sql_files/functions/map/__init__.py
dubai_real_estate/sql_files/functions/map/activity_type_id.sql
dubai_real_estate/sql_files/functions/map/application_id.sql
dubai_real_estate/sql_files/functions/map/area_id.sql
dubai_real_estate/sql_files/functions/map/contract_reg_type_id.sql
dubai_real_estate/sql_files/functions/map/ejari_bus_property_type.sql
dubai_real_estate/sql_files/functions/map/ejari_property_type_id.sql
dubai_real_estate/sql_files/functions/map/escrow_agent_id.sql
dubai_real_estate/sql_files/functions/map/land_type_id.sql
dubai_real_estate/sql_files/functions/map/legal_status_id.sql
dubai_real_estate/sql_files/functions/map/legal_type_id.sql
dubai_real_estate/sql_files/functions/map/license_source_dev_id.sql
dubai_real_estate/sql_files/functions/map/license_source_id.sql
dubai_real_estate/sql_files/functions/map/license_type_id.sql
dubai_real_estate/sql_files/functions/map/main.sql
dubai_real_estate/sql_files/functions/map/market_types.sql
dubai_real_estate/sql_files/functions/map/master_community_id.sql
dubai_real_estate/sql_files/functions/map/nationality_id.sql
dubai_real_estate/sql_files/functions/map/nearest_landmark_id.sql
dubai_real_estate/sql_files/functions/map/nearest_mall_id.sql
dubai_real_estate-0.1.2.dist-info/licenses/LICENSE
dubai_real_estate-0.1.2.dist-info/METADATA
dubai_real_estate-0.1.2.dist-info/WHEEL
dubai_real_estate-0.1.2.dist-info/top_level.txt
dubai_real_estate-0.1.2.dist-info/RECORD
