Metadata-Version: 2.4
Name: dubai_real_estate
Version: 0.1.2
Summary: A comprehensive Python package for working with Dubai real estate data from Dubai Land Department (DLD) through ClickHouse, with beautiful SQL magic commands for Jupyter notebooks.
Author-email: Badr Ouali <badr.ouali@outlook.fr>
Maintainer-email: Badr Ouali <badr.ouali@outlook.fr>
License: Apache-2.0
Project-URL: Homepage, https://github.com/oualib/dubai_real_estate
Project-URL: Repository, https://github.com/oualib/dubai_real_estate
Project-URL: Documentation, https://github.com/oualib/dubai_real_estate
Project-URL: Bug Tracker, https://github.com/oualib/dubai_real_estate/issues
Project-URL: Changelog, https://github.com/oualib/dubai_real_estate/releases
Classifier: Development Status :: 3 - Alpha
Classifier: Intended Audience :: Developers
Classifier: Intended Audience :: Financial and Insurance Industry
Classifier: Intended Audience :: Information Technology
Classifier: Intended Audience :: Science/Research
Classifier: License :: OSI Approved :: Apache Software License
Classifier: Operating System :: OS Independent
Classifier: Programming Language :: Python :: 3
Classifier: Programming Language :: Python :: 3.12
Classifier: Programming Language :: Python :: 3.13
Classifier: Programming Language :: SQL
Classifier: Topic :: Database :: Database Engines/Servers
Classifier: Topic :: Office/Business :: Financial
Classifier: Topic :: Scientific/Engineering :: Information Analysis
Classifier: Topic :: Software Development :: Libraries :: Python Modules
Requires-Python: >=3.12
License-File: LICENSE
Requires-Dist: requests>=2.25.0
Requires-Dist: clickhouse-connect>=0.6.0
Requires-Dist: cryptography>=3.4.0
Requires-Dist: pandas>=1.5.0
Requires-Dist: pathlib
Provides-Extra: dev
Requires-Dist: chdb>=1.0.0; extra == "dev"
Requires-Dist: pytest>=6.0; extra == "dev"
Requires-Dist: pytest-cov>=3.0; extra == "dev"
Requires-Dist: flake8>=6.0; extra == "dev"
Requires-Dist: black; extra == "dev"
Requires-Dist: isort; extra == "dev"
Requires-Dist: mypy; extra == "dev"
Requires-Dist: pre-commit; extra == "dev"
Provides-Extra: jupyter
Requires-Dist: IPython>=7.0.0; extra == "jupyter"
Requires-Dist: jupyter>=1.0.0; extra == "jupyter"
Requires-Dist: notebook>=6.0.0; extra == "jupyter"
Requires-Dist: ipywidgets>=7.0.0; extra == "jupyter"
Provides-Extra: full
Requires-Dist: dubai_real_estate[dev,jupyter]; extra == "full"
Dynamic: license-file
